{
  "id": 252,
  "date": 1676614381,
  "text": "Клиника-заказчик поделилась с нами финальными фотками Трэкола со всем оборудованием. Вроде неплохо получилось. Есть вероятность, что скоро будет ещё заказ на пару передвижных медпунктов.",
  "vk_url": "https://vk.com/siberian_motorbears?w=wall-197853818_252",
  "photos": [
    "entry_110_1.jpg",
    "entry_110_2.jpg",
    "entry_110_3.jpg",
    "entry_110_4.jpg",
    "entry_110_5.jpg",
    "entry_110_6.jpg",
    "entry_110_7.jpg",
    "entry_110_8.jpg",
    "entry_110_9.jpg",
    "entry_110_10.jpg"
  ],
  "video": null
}