{
  "id": 248,
  "date": 1672806827,
  "text": "Трэкол покидает мебельный цех и отправляется на финальный этап работ к электрикам. У него уже есть мигалка, и вся мебель, и освещение, и розеточки, и всякое такое. Через 3-4 дня уже смонтируем специальное медицинское оборудование, и отправим на вахту.",
  "vk_url": "https://vk.com/siberian_motorbears?w=wall-197853818_248",
  "photos": [
    "entry_106_1.jpg",
    "entry_106_2.jpg",
    "entry_106_3.jpg",
    "entry_106_4.jpg",
    "entry_106_5.jpg",
    "entry_106_6.jpg",
    "entry_106_7.jpg"
  ],
  "video": {
    "embed_url": "https://vk.com/video_ext.php?oid=221082&id=456239071"
  }
}