{
  "id": 25,
  "date": 1600270030,
  "text": "Кстати, мы не шутим. Мы действительно собираемся собрать большую команду самых разных моторизированных медведей. И поработить мир, конечно же.\nПока мы обкатываем идею и прощупываем рынок с одним Гризли Грином. Но если зимний сезон не будет совсем пустым, и весенний прокат начнётся бодро, то мы уже знаем, какие два следующих медведя мы станем искать (как и указано у нас на сайте). \nВо-первых, нам нужен большой и комфортабельный шоссейник. Это будет что-то достаточно стандартное, скорее всего европейское. Если повезёт, попробуем даже найти коробку-автомат. \nА вот второе пополнение интереснее. Это будет совершенно отмороженный вездеход для рыболовов, охотников, и просто любителей залезть туда, где Макар телят не гонял. И мы уже определились с шасси для этого медведя, почти точно. Попробуйте угадать! Пара подсказок: это далеко от массового автопрома, это категория \"В\", это допущено на дороги общего пользования, это запросто может пободаться с шишигой или уралом. Что это? \nКто первый даст правильный ответ, тот получит этого нового медведя на сутки бесплатно. Мы сами с ним свяжемся, как только медведь появится в команде.",
  "vk_url": "https://vk.com/siberian_motorbears?w=wall-197853818_25",
  "photos": [],
  "video": null
}